kodicontroller/__init__.py
kodicontroller/kodicontroller.py
kodicontroller-0.0.3.dist-info/DESCRIPTION.rst
kodicontroller-0.0.3.dist-info/METADATA
kodicontroller-0.0.3.dist-info/RECORD
kodicontroller-0.0.3.dist-info/WHEEL
kodicontroller-0.0.3.dist-info/metadata.json
kodicontroller-0.0.3.dist-info/top_level.txt
