Metadata-Version: 2.0
Name: kodicontroller
Version: 0.0.3
Summary: Kodi controller
Home-page: http://github.com/davgeo/kodicontroller
Author: David George
Author-email: dcg.git@gmail.com
License: MIT
Platform: UNKNOWN
Requires-Dist: kodijsonrpc (==1.0)
Requires-Dist: requests (==2.6.0)
